yaxmldiff/__init__.py
yaxmldiff/py.typed
yaxmldiff-0.2.0.dist-info/METADATA
yaxmldiff-0.2.0.dist-info/WHEEL
yaxmldiff-0.2.0.dist-info/licenses/LICENSE.txt
yaxmldiff-0.2.0.dist-info/RECORD
