Metadata-Version: 2.3
Name: yaxmldiff
Version: 0.2.0
Summary: yaxmldiff is Yet Another XML Differ
Project-URL: GitHub, https://github.com/latk/yaxmldiff.py
Project-URL: Issue Tracker, https://github.com/latk/yaxmldiff.py/issues
Author-email: Lukas Atkinson <opensource@LukasAtkinson.de>
License: Apache-2.0
License-File: LICENSE.txt
Keywords: diff,xml
Classifier: Development Status :: 4 - Beta
Classifier: Intended Audience :: Developers
Classifier: License :: OSI Approved :: Apache Software License
Classifier: Programming Language :: Python :: 3
Classifier: Programming Language :: Python :: 3.8
Classifier: Programming Language :: Python :: 3.9
Classifier: Programming Language :: Python :: 3.10
Classifier: Programming Language :: Python :: 3.11
Classifier: Programming Language :: Python :: 3.12
Classifier: Topic :: Software Development :: Testing
Classifier: Topic :: Text Processing :: Markup :: XML
Requires-Python: >=3.8
Requires-Dist: lxml>=3
